torchtils/__init__.py
torchtils/optical_flow/__init__.py
torchtils/optical_flow/horn_schunck.py
torchtils/optical_flow/lucas_kanade.py
torchtils/poisson_image_editing/__init__.py
torchtils/poisson_image_editing/pie.py
torchtils-0.0.33.dist-info/LICENCE.md
torchtils-0.0.33.dist-info/METADATA
torchtils-0.0.33.dist-info/WHEEL
torchtils-0.0.33.dist-info/top_level.txt
torchtils-0.0.33.dist-info/RECORD
